iap_messenger/__init__.py
iap_messenger/config.py
iap_messenger/data_encoder.py
iap_messenger/ddl.py
iap_messenger/decoders.py
iap_messenger/encoders.py
iap_messenger/job_handler.py
iap_messenger/listener.py
iap_messenger/message.py
iap_messenger/readme_handler.py
iap_messenger/subscription.py
iap_messenger/utils.py
iap_messenger-1.5.3.dist-info/licenses/LICENSE
iap_messenger-1.5.3.dist-info/METADATA
iap_messenger-1.5.3.dist-info/WHEEL
iap_messenger-1.5.3.dist-info/top_level.txt
iap_messenger-1.5.3.dist-info/RECORD
