Metadata-Version: 2.4
Name: iap_messenger
Version: 1.5.3
Summary: Messaging service package for IA PARC
Author: Bertrand Louargant
License-Expression: Apache-2.0
Project-URL: Homepage, https://gitlab.com/ia-parc/public/pypi/iap_messenger
Project-URL: Issues, https://gitlab.com/ia-parc/public/pypi/iap_messenger/issues
Classifier: Programming Language :: Python :: 3
Classifier: Operating System :: OS Independent
Requires-Python: >=3.8
License-File: LICENSE
Requires-Dist: nats-py~=2.9.0
Requires-Dist: pillow~=10.4.0
Requires-Dist: pyyaml~=6.0.2
Requires-Dist: yamlcore~=0.0.4
Requires-Dist: asyncio~=3.4.3
Requires-Dist: json-tricks~=3.17.3
Requires-Dist: msgpack~=1.1.0
Requires-Dist: msgpack-numpy~=0.4.8
Requires-Dist: urllib3~=2.2.3
Requires-Dist: lz4~=4.4.4
Requires-Dist: pyzmq~=26.4.0
Dynamic: license-file
